django_permissions_unistra-1.2.5.dist-info/DESCRIPTION.rst
django_permissions_unistra-1.2.5.dist-info/METADATA
django_permissions_unistra-1.2.5.dist-info/RECORD
django_permissions_unistra-1.2.5.dist-info/WHEEL
django_permissions_unistra-1.2.5.dist-info/metadata.json
django_permissions_unistra-1.2.5.dist-info/top_level.txt
permissions/__init__.py
permissions/admin.py
permissions/backend.py
permissions/exceptions.py
permissions/mixins.py
permissions/models.py
permissions/tests.py
permissions/utils.py
permissions/fixtures/initial.xml
permissions/locale/de/LC_MESSAGES/django.mo
permissions/locale/de/LC_MESSAGES/django.po
permissions/migrations/0001_initial.py
permissions/migrations/__init__.py
permissions/templatetags/__init__.py
permissions/templatetags/permissions_tags.py
