Metadata-Version: 2.0
Name: django-permissions-unistra
Version: 1.2.5
Summary: Generic per-object permissions for Django
Home-page: http://www.iqpp.com
Author: Arnaud Grausem
Author-email: arnaud.grausem@unistra.fr
License: BSD
Keywords: django authorization permissions
Platform: UNKNOWN
Classifier: Development Status :: 5 - Production/Stable
Classifier: Environment :: Web Environment
Classifier: Framework :: Django
Classifier: License :: OSI Approved :: BSD License
Classifier: Operating System :: OS Independent
Classifier: Programming Language :: Python
Requires-Dist: setuptools
